pysome/Same.py
pysome/SameState.py
pysome/Some.py
pysome/__init__.py
pysome/exceptions.py
pysome/expect.py
tests/__init__.py
tests/pysome/__init__.py
tests/pysome/test_Same.py
tests/pysome/test_SameState.py
tests/pysome/test_Some.py
tests/pysome/test_expect.py
pysome-0.1.3.dist-info/LICENSE
pysome-0.1.3.dist-info/METADATA
pysome-0.1.3.dist-info/WHEEL
pysome-0.1.3.dist-info/top_level.txt
pysome-0.1.3.dist-info/RECORD
