Metadata-Version: 2.1
Name: pysome
Version: 0.1.3
Summary: flexible testing of nested objects
Home-page: https://github.com/ManuelZierl/pysome
Author: Manuel Zierl
Author-email: manuel.zierl@web.de
License: UNKNOWN
Project-URL: Bug Tracker, https://github.com/ManuelZierl/pysome/issues
Platform: UNKNOWN
Classifier: Programming Language :: Python :: 3
Classifier: License :: OSI Approved :: MIT License
Classifier: Operating System :: OS Independent
Requires-Python: >=3.6
License-File: LICENSE
